ppigrf/IGRF13.shc
ppigrf/IGRF14.shc
ppigrf/__init__.py
ppigrf/ppigrf.py
ppigrf-2.0.0.dist-info/LICENSE
ppigrf-2.0.0.dist-info/METADATA
ppigrf-2.0.0.dist-info/WHEEL
ppigrf-2.0.0.dist-info/top_level.txt
ppigrf-2.0.0.dist-info/RECORD
