Metadata-Version: 2.1
Name: ppigrf
Version: 2.0.0
Summary: Pure Python IGRF
Author: Karl Laundal
Author-email: readme@file.md
Classifier: Development Status :: 4 - Beta
Classifier: Intended Audience :: Science/Research
Classifier: Natural Language :: English
Classifier: Programming Language :: Python :: 3
Requires-Python: >=3.6
License-File: LICENSE
Requires-Dist: numpy>=0.13.1
Requires-Dist: pandas>=1.3.5
